fairseq2n/__init__.py
fairseq2n/bindings.cpython-310-x86_64-linux-gnu.so
fairseq2n/include/fairseq2n/api.h
fairseq2n/include/fairseq2n/config.h
fairseq2n/include/fairseq2n/exception.h
fairseq2n/include/fairseq2n/float.h
fairseq2n/include/fairseq2n/fmt.h
fairseq2n/include/fairseq2n/memory.h
fairseq2n/include/fairseq2n/span.h
fairseq2n/include/fairseq2n/data/bucket_by_length_data_source.h
fairseq2n/include/fairseq2n/data/bucket_data_source.h
fairseq2n/include/fairseq2n/data/byte_stream.h
fairseq2n/include/fairseq2n/data/collater.h
fairseq2n/include/fairseq2n/data/constant_data_source.h
fairseq2n/include/fairseq2n/data/count_data_source.h
fairseq2n/include/fairseq2n/data/data.h
fairseq2n/include/fairseq2n/data/data_length_extractor.h
fairseq2n/include/fairseq2n/data/data_pipeline.h
fairseq2n/include/fairseq2n/data/data_source.h
fairseq2n/include/fairseq2n/data/element_mapper.h
fairseq2n/include/fairseq2n/data/element_selector.h
fairseq2n/include/fairseq2n/data/file.h
fairseq2n/include/fairseq2n/data/file_mapper.h
fairseq2n/include/fairseq2n/data/file_stream.h
fairseq2n/include/fairseq2n/data/filter_data_source.h
fairseq2n/include/fairseq2n/data/immutable_string.h
fairseq2n/include/fairseq2n/data/list_data_source.h
fairseq2n/include/fairseq2n/data/map_data_source.h
fairseq2n/include/fairseq2n/data/memory_stream.h
fairseq2n/include/fairseq2n/data/prefetch_data_source.h
fairseq2n/include/fairseq2n/data/py.h
fairseq2n/include/fairseq2n/data/record_reader.h
fairseq2n/include/fairseq2n/data/round_robin_data_source.h
fairseq2n/include/fairseq2n/data/shard_data_source.h
fairseq2n/include/fairseq2n/data/shuffle_data_source.h
fairseq2n/include/fairseq2n/data/skip_data_source.h
fairseq2n/include/fairseq2n/data/take_data_source.h
fairseq2n/include/fairseq2n/data/tape-inl.h
fairseq2n/include/fairseq2n/data/tape.h
fairseq2n/include/fairseq2n/data/yield_from_data_source.h
fairseq2n/include/fairseq2n/data/zip_data_source.h
fairseq2n/include/fairseq2n/data/zip_file_data_source.h
fairseq2n_patch-0.1.1.dist-info/METADATA
fairseq2n_patch-0.1.1.dist-info/WHEEL
fairseq2n_patch-0.1.1.dist-info/top_level.txt
fairseq2n_patch-0.1.1.dist-info/RECORD
