Metadata-Version: 2.1
Name: fairseq2n-patch
Version: 0.1.1
Summary: FAIR Sequence Modeling Toolkit (Native)
Home-page: https://github.com/facebookresearch/fairseq2
Author: Fundamental AI Research (FAIR) at Meta
License: MIT
Keywords: machine learning
Classifier: Development Status :: 4 - Beta
Classifier: Intended Audience :: Developers
Classifier: Intended Audience :: Science/Research
Classifier: License :: OSI Approved :: MIT License
Classifier: Programming Language :: Python :: 3
Classifier: Programming Language :: Python :: 3.8
Classifier: Programming Language :: Python :: 3.9
Classifier: Programming Language :: Python :: 3.10
Classifier: Programming Language :: Python :: 3.11
Classifier: Topic :: Scientific/Engineering :: Artificial Intelligence
Requires-Python: >=3.8
Requires-Dist: torch ==2.1.0
Requires-Dist: tbb <2021.10,>=2021.8 ; platform_machine == "x86_64"
